Workbook

Sheet Como usar
A1: Casos de teste · Sistema Mulheres & Quintais
A2: Versão do sistema testada: mq-v98 (setembro de 2026) · 100 casos
A4: Como usar
A5: 1. Cada linha da aba "Casos de teste" é uma coisa para testar. Faça os passos com o perfil indicado e compare com o "Resultado esperado".
A6: 2. A coluna Prioridade diz o que testar primeiro: Crítica, depois Alta, depois Média. Preencha só as colunas com fundo amarelo: Celular e navegador, Testado por, Data, Resultado e Observação.
A7: 3. Em Resultado, escolha: Passou, Falhou, Bloqueado (não deu para testar, por exemplo por falta de pré-condição) ou Não testado.
A8: 4. Quando falhar: escreva em Observação o que apareceu na tela e mande um print da tela para a coordenação geral, citando o ID do caso (ex.: F05).
A9: 5. Teste no celular de verdade de quem vai usar: pelo menos um Android (Chrome) e um iPhone (Safari).
A10: 6. Os casos sem internet (A10, A14, S02, F05, F13) devem ser feitos com o celular em modo avião, de preferência no campo.
A11: 7. A aba "Resumo" conta sozinha quantos passaram e falharam em cada área.
A13: Antes de começar
A14: • Use dados inventados. Nunca teste com CPF, nome ou foto de uma mulher real.
... A16: • O caso A01 tem uma linha de exemplo já preenchida, para mostrar o formato. Apague ou substitua pelo seu resultado.

Sheet Casos de teste
A1: ID | B1: Perfil | C1: Área | D1: O que testar | E1: Pré-condição | F1: Passos | G1: Resultado esperado | H1: Prioridade | I1: Celular e navegador | J1: Testado por | K1: Data | L1: Resultado | M1: Observação
A2: A01 | B2: Coordenação geral | C2: Acesso e login | D2: Gerar código de acesso | E2: Pessoa cadastrada que ainda não criou senha | F2: Equipe → abrir a ficha da pessoa → Gerar código de acesso → Mandar por WhatsApp | G2: Aparece o código (ex.: ABCD-2345, vale 7 dias) e a mensagem pronta com endereço, e-mail e código | H2: Crítica | I2: Moto G, Chrome | J2: Exemplo | K2: 46294 | L2: Passou | M2: Exemplo de preenchimento: substitua pelo seu teste.
A3: A02 | B3: Qualquer perfil novo | C3: Acesso e login | D3: Primeiro acesso com código certo | E3: Ter recebido o código (A01) | F3: Tela de entrada → Primeiro acesso → e-mail, código e senha (2 vezes) → Criar senha e entrar | G3: Entra no sistema e vê só as telas do seu perfil | H3: Crítica | L3: Não testado
A4: A03 | B4: Qualquer perfil novo | C4: Acesso e login | D4: Primeiro acesso com código errado | E4: Pessoa cadastrada, sem senha | F4: Primeiro acesso → e-mail certo e código inventado | G4: Recusa com a mensagem "confira o e-mail e o código de acesso". Não cria senha | H4: Crítica | L4: Não testado
A5: A04 | B5: Pessoa de fora | C5: Acesso e login | D5: Tentar entrar no lugar de outra pessoa | E5: Saber o e-mail de alguém cadastrado que ainda não entrou | F5: Primeiro acesso com o e-mail dessa pessoa, sem o código dela | G5: Recusado. Sem o código ninguém cria a senha | H5: Crítica | L5: Não testado
A6: A05 | B6: Qualquer perfil | C6: Acesso e login | D6: Usar o mesmo código duas vezes | E6: Já ter feito o A02 | F6: Sair → Primeiro acesso de novo com o mesmo e-mail e código | G6: Aparece "Este e-mail já tem senha" | H6: Alta | L6: Não testado
A7: A06 | B7: Coordenação geral | C7: Acesso e login | D7: Liberar novo acesso (esqueceu a senha) | E7: Pessoa que já tem senha | F7: Ficha da pessoa → Liberar novo primeiro acesso → Confirmar → mandar o código novo; a pessoa faz o Primeiro acesso | G7: Senha antiga deixa de funcionar; a nova funciona; os dados da pessoa continuam iguais; o Histórico registra | H7: Crítica | L7: Não testado
A8: A07 | B8: Coordenação técnica | C8: Acesso e login | D8: Não pode liberar novo acesso | E8: Bolsista que já tem senha | F8: Abrir a ficha da bolsista | G8: O botão "Liberar novo primeiro acesso" não aparece | H8: Alta | L8: Não testado
A9: A08 | B9: Todos (um login por perfil) | C9: Acesso e login | D9: Cada perfil vê só as suas telas | E9: Um login de cada perfil | F9: Entrar com cada login e anotar as abas | G9: Coord. geral: 8 abas. Coord. técnica: Seleção, Equipe, Campo, Pagamentos, Custos. Bolsista, agente, professor e auxiliar: só a própria tela | H9: Crítica | L9: Não testado
A10: A09 | B10: Qualquer perfil | C10: Acesso e login | D10: Continuar na mesma tela ao recarregar | E10: Estar em uma aba que não é a primeira | F10: Recarregar a página (puxar a tela para baixo no celular) | G10: Volta na mesma aba e na mesma altura da página | H10: Média | L10: Não testado
A11: A10 | B11: Bolsista | C11: Acesso e login | D11: Sair sem internet | E11: Celular em modo avião | F11: Tocar em Sair | G11: Pede confirmação ("Sair mesmo?") e avisa que só volta a entrar com internet | H11: Alta | L11: Não testado
A12: A11 | B12: Qualquer perfil | C12: Acesso e login | D12: Senha errada | E12: Pessoa com senha | F12: Já tenho senha → senha errada | G12: "E-mail ou senha incorretos"; não entra | H12: Alta | L12: Não testado
A13: A12 | B13: Coordenação geral | C13: Acesso e login | D13: Código vencido | E13: Código gerado para uma pessoa sem senha | F13: No SQL Editor: update public.acesso_codigos set expira_em = now() - interval '1 minute'; depois tentar o Primeiro acesso | G13: Recusado; um código novo funciona | H13: Alta | L13: Não testado
A14: A13 | B14: Qualquer perfil novo | C14: Acesso e login | D14: E-mail digitado diferente | E14: Código recebido | F14: Primeiro acesso com o e-mail em maiúsculas ou com espaço no fim | G14: Aceita (o sistema ignora maiúsculas e espaços) | H14: Média | L14: Não testado
... A101: K08 | B101: Pessoa de fora | C101: Custos e vitrine pública | D101: O projeto em números sem login | E101: Navegador sem login | F101: Abrir o endereço do sistema com #numeros no final | G101: Mostra os números do projeto sem pedir senha e sem nenhum dado pessoal | H101: Crítica | L101: Não testado

Sheet Resumo
A1: Área | B1: Casos | C1: Passou | D1: Falhou | E1: Bloqueado | F1: Não testado | G1: % testado | H1: % que passou (dos testados)
A2: Acesso e login | B2: =COUNTIF('Casos de teste'!$C$2:$C$101,A2) | C2: =COUNTIFS('Casos de teste'!$C$2:$C$101,$A2,'Casos de teste'!$L$2:$L$101,"Passou") | D2: =COUNTIFS('Casos de teste'!$C$2:$C$101,$A2,'Casos de teste'!$L$2:$L$101,"Falhou") | E2: =COUNTIFS('Casos de teste'!$C$2:$C$101,$A2,'Casos de teste'!$L$2:$L$101,"Bloqueado") | F2: =COUNTIFS('Casos de teste'!$C$2:$C$101,$A2,'Casos de teste'!$L$2:$L$101,"Não testado") | G2: =IF(B2=0,0,(C2+D2)/B2) | H2: =IF(C2+D2=0,"-",C2/(C2+D2))
A3: Cadastro da equipe | B3: =COUNTIF('Casos de teste'!$C$2:$C$101,A3) | C3: =COUNTIFS('Casos de teste'!$C$2:$C$101,$A3,'Casos de teste'!$L$2:$L$101,"Passou") | D3: =COUNTIFS('Casos de teste'!$C$2:$C$101,$A3,'Casos de teste'!$L$2:$L$101,"Falhou") | E3: =COUNTIFS('Casos de teste'!$C$2:$C$101,$A3,'Casos de teste'!$L$2:$L$101,"Bloqueado") | F3: =COUNTIFS('Casos de teste'!$C$2:$C$101,$A3,'Casos de teste'!$L$2:$L$101,"Não testado") | G3: =IF(B3=0,0,(C3+D3)/B3) | H3: =IF(C3+D3=0,"-",C3/(C3+D3))
A4: Pendências, guia e ajuda | B4: =COUNTIF('Casos de teste'!$C$2:$C$101,A4) | C4: =COUNTIFS('Casos de teste'!$C$2:$C$101,$A4,'Casos de teste'!$L$2:$L$101,"Passou") | D4: =COUNTIFS('Casos de teste'!$C$2:$C$101,$A4,'Casos de teste'!$L$2:$L$101,"Falhou") | E4: =COUNTIFS('Casos de teste'!$C$2:$C$101,$A4,'Casos de teste'!$L$2:$L$101,"Bloqueado") | F4: =COUNTIFS('Casos de teste'!$C$2:$C$101,$A4,'Casos de teste'!$L$2:$L$101,"Não testado") | G4: =IF(B4=0,0,(C4+D4)/B4) | H4: =IF(C4+D4=0,"-",C4/(C4+D4))
A5: Seleção das mulheres | B5: =COUNTIF('Casos de teste'!$C$2:$C$101,A5) | C5: =COUNTIFS('Casos de teste'!$C$2:$C$101,$A5,'Casos de teste'!$L$2:$L$101,"Passou") | D5: =COUNTIFS('Casos de teste'!$C$2:$C$101,$A5,'Casos de teste'!$L$2:$L$101,"Falhou") | E5: =COUNTIFS('Casos de teste'!$C$2:$C$101,$A5,'Casos de teste'!$L$2:$L$101,"Bloqueado") | F5: =COUNTIFS('Casos de teste'!$C$2:$C$101,$A5,'Casos de teste'!$L$2:$L$101,"Não testado") | G5: =IF(B5=0,0,(C5+D5)/B5) | H5: =IF(C5+D5=0,"-",C5/(C5+D5))
A6: Trabalho de campo | B6: =COUNTIF('Casos de teste'!$C$2:$C$101,A6) | C6: =COUNTIFS('Casos de teste'!$C$2:$C$101,$A6,'Casos de teste'!$L$2:$L$101,"Passou") | D6: =COUNTIFS('Casos de teste'!$C$2:$C$101,$A6,'Casos de teste'!$L$2:$L$101,"Falhou") | E6: =COUNTIFS('Casos de teste'!$C$2:$C$101,$A6,'Casos de teste'!$L$2:$L$101,"Bloqueado") | F6: =COUNTIFS('Casos de teste'!$C$2:$C$101,$A6,'Casos de teste'!$L$2:$L$101,"Não testado") | G6: =IF(B6=0,0,(C6+D6)/B6) | H6: =IF(C6+D6=0,"-",C6/(C6+D6))
A7: Curso FIC e entregas do mês | B7: =COUNTIF('Casos de teste'!$C$2:$C$101,A7) | C7: =COUNTIFS('Casos de teste'!$C$2:$C$101,$A7,'Casos de teste'!$L$2:$L$101,"Passou") | D7: =COUNTIFS('Casos de teste'!$C$2:$C$101,$A7,'Casos de teste'!$L$2:$L$101,"Falhou") | E7: =COUNTIFS('Casos de teste'!$C$2:$C$101,$A7,'Casos de teste'!$L$2:$L$101,"Bloqueado") | F7: =COUNTIFS('Casos de teste'!$C$2:$C$101,$A7,'Casos de teste'!$L$2:$L$101,"Não testado") | G7: =IF(B7=0,0,(C7+D7)/B7) | H7: =IF(C7+D7=0,"-",C7/(C7+D7))
A8: Pagamentos | B8: =COUNTIF('Casos de teste'!$C$2:$C$101,A8) | C8: =COUNTIFS('Casos de teste'!$C$2:$C$101,$A8,'Casos de teste'!$L$2:$L$101,"Passou") | D8: =COUNTIFS('Casos de teste'!$C$2:$C$101,$A8,'Casos de teste'!$L$2:$L$101,"Falhou") | E8: =COUNTIFS('Casos de teste'!$C$2:$C$101,$A8,'Casos de teste'!$L$2:$L$101,"Bloqueado") | F8: =COUNTIFS('Casos de teste'!$C$2:$C$101,$A8,'Casos de teste'!$L$2:$L$101,"Não testado") | G8: =IF(B8=0,0,(C8+D8)/B8) | H8: =IF(C8+D8=0,"-",C8/(C8+D8))
A9: Coordenação e uso geral | B9: =COUNTIF('Casos de teste'!$C$2:$C$101,A9) | C9: =COUNTIFS('Casos de teste'!$C$2:$C$101,$A9,'Casos de teste'!$L$2:$L$101,"Passou") | D9: =COUNTIFS('Casos de teste'!$C$2:$C$101,$A9,'Casos de teste'!$L$2:$L$101,"Falhou") | E9: =COUNTIFS('Casos de teste'!$C$2:$C$101,$A9,'Casos de teste'!$L$2:$L$101,"Bloqueado") | F9: =COUNTIFS('Casos de teste'!$C$2:$C$101,$A9,'Casos de teste'!$L$2:$L$101,"Não testado") | G9: =IF(B9=0,0,(C9+D9)/B9) | H9: =IF(C9+D9=0,"-",C9/(C9+D9))
A10: Custos e vitrine pública | B10: =COUNTIF('Casos de teste'!$C$2:$C$101,A10) | C10: =COUNTIFS('Casos de teste'!$C$2:$C$101,$A10,'Casos de teste'!$L$2:$L$101,"Passou") | D10: =COUNTIFS('Casos de teste'!$C$2:$C$101,$A10,'Casos de teste'!$L$2:$L$101,"Falhou") | E10: =COUNTIFS('Casos de teste'!$C$2:$C$101,$A10,'Casos de teste'!$L$2:$L$101,"Bloqueado") | F10: =COUNTIFS('Casos de teste'!$C$2:$C$101,$A10,'Casos de teste'!$L$2:$L$101,"Não testado") | G10: =IF(B10=0,0,(C10+D10)/B10) | H10: =IF(C10+D10=0,"-",C10/(C10+D10))
A11: Total | B11: =SUM(B2:B10) | C11: =SUM(C2:C10) | D11: =SUM(D2:D10) | E11: =SUM(E2:E10) | F11: =SUM(F2:F10) | G11: =IF(B11=0,0,(C11+D11)/B11) | H11: =IF(C11+D11=0,"-",C11/(C11+D11))
A13: Conta sozinho a partir da coluna Resultado da aba "Casos de teste". "Bloqueado" e "Não testado" não entram no % que passou.
A14: Falhas abertas (IDs): | B14: {=IFERROR(_xlfn.TEXTJOIN(", ",TRUE,IF('Casos de teste'!$L$2:$L$101="Falhou",'Casos de teste'!$A$2:$A$101,"")),"")}
